[{"STATE":"Alabama","Alabama":"N/A","Alaska":"576","Arizona":"1,022","Arkansas":"495","California":"6,611","Colorado":"2,177","Connecticut":"566","Delaware":"0","DC":"97","Florida":"16,631","Georgia":"23,008","Hawaii":"1,695","Idaho":"212","Illinois":"3,707","Indiana":"1,445","Iowa":"671","Kansas":"1,261","Kentucky":"1,590","Louisiana":"1,508","Maine":"151","Maryland":"1,903","Massachusetts":"330","Michigan":"2,195","Minnesota":"122","Mississippi":"7,602","Missouri":"2,746","Montana":"294","Nebraska":"33","Nevada":"254","New Hampshire":"0","New Jersey":"812","New Mexico":"826","New York":"3,047","North Carolina":"6,419","North Dakota":"0","Ohio":"2,694","Oklahoma":"1,169","Oregon":"498","Pennsylvania":"1,008","Rhode Island":"0","South Carolina":"2,952","South Dakota":"52","Tennessee":"9,960","Texas":"7,689","Utah":"525","Vermont":"0","Virginia":"3,535","Washington":"677","West Virginia":"42","Wisconsin":"874","Wyoming":"539","Puerto Rico":"335"},{"STATE":"Alaska","Alabama":"423","Alaska":"N/A","Arizona":"1,176","Arkansas":"65","California":"3,593","Colorado":"1,401","Connecticut":"0","Delaware":"79","DC":"0","Florida":"1,100","Georgia":"2,208","Hawaii":"561","Idaho":"361","Illinois":"715","Indiana":"126","Iowa":"142","Kansas":"1,831","Kentucky":"703","Louisiana":"273","Maine":"147","Maryland":"0","Massachusetts":"44","Michigan":"133","Minnesota":"236","Mississippi":"92","Missouri":"281","Montana":"832","Nebraska":"0","Nevada":"534","New Hampshire":"32","New Jersey":"270","New Mexico":"198","New York":"910","North Carolina":"714","North Dakota":"58","Ohio":"100","Oklahoma":"806","Oregon":"1,301","Pennsylvania":"574","Rhode Island":"0","South Carolina":"281","South Dakota":"370","Tennessee":"243","Texas":"1,675","Utah":"725","Vermont":"86","Virginia":"462","Washington":"4,888","West Virginia":"0","Wisconsin":"260","Wyoming":"291","Puerto Rico":"848"},{"STATE":"Arizona","Alabama":"894","Alaska":"1,946","Arizona":"N/A","Arkansas":"1,205","California":"64,756","Colorado":"11,895","Connecticut":"1,596","Delaware":"420","DC":"276","Florida":"9,306","Georgia":"4,242","Hawaii":"2,339","Idaho":"2,775","Illinois":"13,387","Indiana":"5,443","Iowa":"2,649","Kansas":"3,383","Kentucky":"1,105","Louisiana":"679","Maine":"355","Maryland":"1,467","Massachusetts":"4,028","Michigan":"6,525","Minnesota":"5,461","Mississippi":"568","Missouri":"3,708","Montana":"2,414","Nebraska":"1,312","Nevada":"7,350","New Hampshire":"224","New Jersey":"3,971","New Mexico":"9,453","New York":"3,029","North Carolina":"4,605","North Dakota":"1,662","Ohio":"3,839","Oklahoma":"7,494","Oregon":"9,279","Pennsylvania":"4,651","Rhode Island":"51","South Carolina":"1,768","South Dakota":"2,408","Tennessee":"1,834","Texas":"14,923","Utah":"9,979","Vermont":"817","Virginia":"8,809","Washington":"13,897","West Virginia":"1,419","Wisconsin":"6,736","Wyoming":"925","Puerto Rico":"1,462"},{"STATE":"Arkansas","Alabama":"2,057","Alaska":"103","Arizona":"836","Arkansas":"N/A","California":"4,026","Colorado":"3,459","Connecticut":"186","Delaware":"0","DC":"69","Florida":"1,351","Georgia":"2,683","Hawaii":"241","Idaho":"0","Illinois":"2,594","Indiana":"335","Iowa":"1,115","Kansas":"979","Kentucky":"1,356","Louisiana":"3,530","Maine":"178","Maryland":"319","Massachusetts":"302","Michigan":"928","Minnesota":"449","Mississippi":"3,699","Missouri":"6,911","Montana":"36","Nebraska":"1,411","Nevada":"1,194","New Hampshire":"0","New Jersey":"250","New Mexico":"225","New York":"590","North Carolina":"939","North Dakota":"39","Ohio":"192","Oklahoma":"5,773","Oregon":"389","Pennsylvania":"1,146","Rhode Island":"0","South Carolina":"70","South Dakota":"0","Tennessee":"2,635","Texas":"13,487","Utah":"619","Vermont":"0","Virginia":"1,333","Washington":"2,257","West Virginia":"75","Wisconsin":"539","Wyoming":"178","Puerto Rico":"857"},{"STATE":"California","Alabama":"3,045","Alaska":"4,206","Arizona":"33,757","Arkansas":"4,282","California":"N/A","Colorado":"22,540","Connecticut":"2,932","Delaware":"1,372","DC":"6,319","Florida":"25,354","Georgia":"14,663","Hawaii":"14,239","Idaho":"3,598","Illinois":"21,539","Indiana":"7,073","Iowa":"3,826","Kansas":"3,293","Kentucky":"4,206","Louisiana":"4,933","Maine":"2,513","Maryland":"10,637","Massachusetts":"14,062","Michigan":"11,442","Minnesota":"10,897","Mississippi":"3,174","Missouri":"7,580","Montana":"1,272","Nebraska":"1,876","Nevada":"24,656","New Hampshire":"889","New Jersey":"11,988","New Mexico":"8,087","New York":"40,877","North Carolina":"14,268","North Dakota":"2,664","Ohio":"9,652","Oklahoma":"6,023","Oregon":"18,919","Pennsylvania":"13,090","Rhode Island":"2,265","South Carolina":"5,137","South Dakota":"1,333","Tennessee":"6,158","Texas":"39,109","Utah":"11,114","Vermont":"400","Virginia":"14,348","Washington":"27,973","West Virginia":"1,150","Wisconsin":"7,354","Wyoming":"2,674","Puerto Rico":"1,102"},{"STATE":"Colorado","Alabama":"2,328","Alaska":"1,698","Arizona":"13,015","Arkansas":"808","California":"26,909","Colorado":"N/A","Connecticut":"2,882","Delaware":"0","DC":"1,360","Florida":"13,546","Georgia":"6,128","Hawaii":"2,795","Idaho":"1,565","Illinois":"11,369","Indiana":"2,672","Iowa":"3,243","Kansas":"4,634","Kentucky":"1,736","Louisiana":"3,361","Maine":"390","Maryland":"3,467","Massachusetts":"2,196","Michigan":"4,285","Minnesota":"3,725","Mississippi":"1,319","Missouri":"6,246","Montana":"1,334","Nebraska":"3,050","Nevada":"4,366","New Hampshire":"1,360","New Jersey":"2,731","New Mexico":"5,073","New York":"8,612","North Carolina":"6,059","North Dakota":"1,801","Ohio":"3,674","Oklahoma":"3,828","Oregon":"3,473","Pennsylvania":"4,586","Rhode Island":"63","South Carolina":"1,945","South Dakota":"1,735","Tennessee":"4,035","Texas":"20,725","Utah":"3,642","Vermont":"647","Virginia":"7,148","Washington":"4,487","West Virginia":"309","Wisconsin":"3,243","Wyoming":"3,657","Puerto Rico":"751"},{"STATE":"Connecticut","Alabama":"1,102","Alaska":"331","Arizona":"309","Arkansas":"960","California":"3,979","Colorado":"562","Connecticut":"N/A","Delaware":"0","DC":"433","Florida":"4,629","Georgia":"1,129","Hawaii":"449","Idaho":"0","Illinois":"1,733","Indiana":"488","Iowa":"162","Kansas":"329","Kentucky":"43","Louisiana":"330","Maine":"941","Maryland":"1,716","Massachusetts":"8,519","Michigan":"614","Minnesota":"780","Mississippi":"0","Missouri":"248","Montana":"0","Nebraska":"0","Nevada":"34","New Hampshire":"750","New Jersey":"4,496","New Mexico":"0","New York":"22,160","North Carolina":"1,651","North Dakota":"64","Ohio":"1,124","Oklahoma":"45","Oregon":"62","Pennsylvania":"3,427","Rhode Island":"3,255","South Carolina":"1,054","South Dakota":"0","Tennessee":"394","Texas":"2,679","Utah":"0","Vermont":"1,131","Virginia":"2,320","Washington":"631","West Virginia":"286","Wisconsin":"237","Wyoming":"0","Puerto Rico":"3,066"},{"STATE":"Delaware","Alabama":"148","Alaska":"80","Arizona":"22","Arkansas":"0","California":"598","Colorado":"106","Connecticut":"1,263","Delaware":"N/A","DC":"113","Florida":"708","Georgia":"293","Hawaii":"68","Idaho":"30","Illinois":"953","Indiana":"26","Iowa":"0","Kansas":"0","Kentucky":"36","Louisiana":"0","Maine":"116","Maryland":"6,985","Massachusetts":"509","Michigan":"11","Minnesota":"0","Mississippi":"105","Missouri":"230","Montana":"94","Nebraska":"0","Nevada":"27","New Hampshire":"0","New Jersey":"5,656","New Mexico":"0","New York":"2,218","North Carolina":"338","North Dakota":"0","Ohio":"272","Oklahoma":"0","Oregon":"0","Pennsylvania":"10,139","Rhode Island":"0","South Carolina":"212","South Dakota":"23","Tennessee":"34","Texas":"515","Utah":"0","Vermont":"112","Virginia":"1,021","Washington":"181","West Virginia":"158","Wisconsin":"0","Wyoming":"0","Puerto Rico":"666"},{"STATE":"DC","Alabama":"140","Alaska":"77","Arizona":"744","Arkansas":"0","California":"3,908","Colorado":"531","Connecticut":"1,225","Delaware":"278","DC":"N/A","Florida":"2,717","Georgia":"1,105","Hawaii":"103","Idaho":"0","Illinois":"2,418","Indiana":"957","Iowa":"218","Kansas":"0","Kentucky":"233","Louisiana":"197","Maine":"118","Maryland":"12,778","Massachusetts":"1,974","Michigan":"922","Minnesota":"542","Mississippi":"224","Missouri":"566","Montana":"17","Nebraska":"190","Nevada":"356","New Hampshire":"168","New Jersey":"1,494","New Mexico":"1","New York":"4,762","North Carolina":"1,367","North Dakota":"83","Ohio":"659","Oklahoma":"122","Oregon":"125","Pennsylvania":"2,468","Rhode Island":"268","South Carolina":"382","South Dakota":"0","Tennessee":"452","Texas":"2,213","Utah":"249","Vermont":"0","Virginia":"9,847","Washington":"418","West Virginia":"296","Wisconsin":"242","Wyoming":"0","Puerto Rico":"351"},{"STATE":"Florida","Alabama":"11,353","Alaska":"1,852","Arizona":"10,312","Arkansas":"4,136","California":"28,420","Colorado":"9,880","Connecticut":"15,285","Delaware":"3,143","DC":"1,752","Florida":"N/A","Georgia":"39,578","Hawaii":"1,326","Idaho":"885","Illinois":"23,319","Indiana":"14,370","Iowa":"6,630","Kansas":"2,392","Kentucky":"8,588","Louisiana":"5,375","Maine":"2,859","Maryland":"17,648","Massachusetts":"19,882","Michigan":"19,530","Minnesota":"6,778","Mississippi":"6,621","Missouri":"11,656","Montana":"677","Nebraska":"1,870","Nevada":"4,273","New Hampshire":"5,292","New Jersey":"33,966","New Mexico":"3,091","New York":"60,472","North Carolina":"28,726","North Dakota":"1,127","Ohio":"29,655","Oklahoma":"3,124","Oregon":"1,258","Pennsylvania":"30,258","Rhode Island":"4,894","South Carolina":"15,904","South Dakota":"535","Tennessee":"18,647","Texas":"31,153","Utah":"3,531","Vermont":"1,627","Virginia":"29,485","Washington":"6,152","West Virginia":"3,979","Wisconsin":"11,298","Wyoming":"454","Puerto Rico":"24,132"},{"STATE":"Georgia","Alabama":"18,276","Alaska":"1,287","Arizona":"3,901","Arkansas":"2,388","California":"18,948","Colorado":"3,337","Connecticut":"6,077","Delaware":"1,294","DC":"1,473","Florida":"44,846","Georgia":"N/A","Hawaii":"768","Idaho":"935","Illinois":"7,630","Indiana":"1,872","Iowa":"2,123","Kansas":"2,003","Kentucky":"4,049","Louisiana":"6,951","Maine":"815","Maryland":"6,600","Massachusetts":"5,727","Michigan":"4,744","Minnesota":"3,166","Mississippi":"5,796","Missouri":"3,775","Montana":"294","Nebraska":"566","Nevada":"900","New Hampshire":"577","New Jersey":"5,201","New Mexico":"1,188","New York":"24,772","North Carolina":"17,750","North Dakota":"436","Ohio":"11,319","Oklahoma":"1,932","Oregon":"2,212","Pennsylvania":"8,370","Rhode Island":"399","South Carolina":"11,199","South Dakota":"336","Tennessee":"20,161","Texas":"19,994","Utah":"923","Vermont":"730","Virginia":"11,597","Washington":"3,270","West Virginia":"838","Wisconsin":"1,273","Wyoming":"22","Puerto Rico":"2,626"},{"STATE":"Hawaii","Alabama":"1,182","Alaska":"672","Arizona":"1,852","Arkansas":"155","California":"13,047","Colorado":"1,643","Connecticut":"269","Delaware":"54","DC":"458","Florida":"2,113","Georgia":"2,487","Hawaii":"N/A","Idaho":"94","Illinois":"2,301","Indiana":"930","Iowa":"50","Kansas":"706","Kentucky":"265","Louisiana":"305","Maine":"0","Maryland":"1,098","Massachusetts":"487","Michigan":"379","Minnesota":"464","Mississippi":"48","Missouri":"204","Montana":"282","Nebraska":"190","Nevada":"1,491","New Hampshire":"0","New Jersey":"723","New Mexico":"841","New York":"1,654","North Carolina":"2,395","North Dakota":"0","Ohio":"602","Oklahoma":"0","Oregon":"883","Pennsylvania":"836","Rhode Island":"340","South Carolina":"2,528","South Dakota":"0","Tennessee":"1,582","Texas":"4,485","Utah":"589","Vermont":"83","Virginia":"2,033","Washington":"4,355","West Virginia":"20","Wisconsin":"54","Wyoming":"0","Puerto Rico":"0"},{"STATE":"Idaho","Alabama":"0","Alaska":"1,638","Arizona":"4,322","Arkansas":"341","California":"17,019","Colorado":"3,072","Connecticut":"49","Delaware":"0","DC":"0","Florida":"1,356","Georgia":"458","Hawaii":"1,113","Idaho":"N/A","Illinois":"757","Indiana":"158","Iowa":"480","Kansas":"133","Kentucky":"188","Louisiana":"379","Maine":"200","Maryland":"281","Massachusetts":"423","Michigan":"382","Minnesota":"426","Mississippi":"0","Missouri":"390","Montana":"1,425","Nebraska":"65","Nevada":"3,300","New Hampshire":"46","New Jersey":"284","New Mexico":"1,508","New York":"671","North Carolina":"2,116","North Dakota":"708","Ohio":"381","Oklahoma":"178","Oregon":"2,836","Pennsylvania":"1,062","Rhode Island":"0","South Carolina":"93","South Dakota":"142","Tennessee":"60","Texas":"2,606","Utah":"7,405","Vermont":"0","Virginia":"401","Washington":"9,303","West Virginia":"122","Wisconsin":"249","Wyoming":"3,030","Puerto Rico":"0"},{"STATE":"Illinois","Alabama":"2,022","Alaska":"578","Arizona":"5,251","Arkansas":"1,288","California":"15,163","Colorado":"3,257","Connecticut":"1,297","Delaware":"205","DC":"1,083","Florida":"13,021","Georgia":"6,739","Hawaii":"627","Idaho":"724","Illinois":"N/A","Indiana":"15,203","Iowa":"9,541","Kansas":"2,683","Kentucky":"3,791","Louisiana":"1,219","Maine":"180","Maryland":"2,140","Massachusetts":"3,651","Michigan":"8,176","Minnesota":"3,566","Mississippi":"1,608","Missouri":"16,251","Montana":"530","Nebraska":"1,214","Nevada":"1,476","New Hampshire":"741","New Jersey":"2,733","New Mexico":"309","New York":"7,566","North Carolina":"4,379","North Dakota":"372","Ohio":"7,260","Oklahoma":"732","Oregon":"1,025","Pennsylvania":"3,809","Rhode Island":"358","South Carolina":"954","South Dakota":"447","Tennessee":"6,928","Texas":"13,290","Utah":"1,211","Vermont":"919","Virginia":"7,822","Washington":"3,628","West Virginia":"880","Wisconsin":"15,595","Wyoming":"271","Puerto Rico":"1,793"},{"STATE":"Indiana","Alabama":"1,133","Alaska":"495","Arizona":"1,185","Arkansas":"1,308","California":"6,970","Colorado":"1,513","Connecticut":"884","Delaware":"401","DC":"64","Florida":"10,994","Georgia":"4,503","Hawaii":"1,426","Idaho":"217","Illinois":"29,883","Indiana":"N/A","Iowa":"1,496","Kansas":"1,520","Kentucky":"9,978","Louisiana":"584","Maine":"712","Maryland":"1,521","Massachusetts":"926","Michigan":"8,950","Minnesota":"1,989","Mississippi":"1,568","Missouri":"2,363","Montana":"0","Nebraska":"108","Nevada":"480","New Hampshire":"575","New Jersey":"4,923","New Mexico":"645","New York":"2,583","North Carolina":"4,496","North Dakota":"498","Ohio":"13,303","Oklahoma":"645","Oregon":"1,386","Pennsylvania":"2,165","Rhode Island":"0","South Carolina":"1,630","South Dakota":"0","Tennessee":"2,979","Texas":"9,403","Utah":"254","Vermont":"119","Virginia":"3,188","Washington":"1,203","West Virginia":"156","Wisconsin":"2,460","Wyoming":"0","Puerto Rico":"34"},{"STATE":"Iowa","Alabama":"395","Alaska":"662","Arizona":"1,556","Arkansas":"315","California":"2,380","Colorado":"3,478","Connecticut":"60","Delaware":"0","DC":"14","Florida":"1,749","Georgia":"866","Hawaii":"30","Idaho":"566","Illinois":"14,948","Indiana":"1,876","Iowa":"N/A","Kansas":"1,871","Kentucky":"1,255","Louisiana":"573","Maine":"410","Maryland":"538","Massachusetts":"170","Michigan":"944","Minnesota":"7,633","Mississippi":"594","Missouri":"6,509","Montana":"301","Nebraska":"6,812","Nevada":"702","New Hampshire":"77","New Jersey":"1,028","New Mexico":"412","New York":"807","North Carolina":"1,755","North Dakota":"1,008","Ohio":"1,261","Oklahoma":"754","Oregon":"16","Pennsylvania":"710","Rhode Island":"25","South Carolina":"138","South Dakota":"1,192","Tennessee":"1,256","Texas":"3,437","Utah":"496","Vermont":"137","Virginia":"663","Washington":"1,662","West Virginia":"203","Wisconsin":"3,848","Wyoming":"171","Puerto Rico":"12"},{"STATE":"Kansas","Alabama":"879","Alaska":"291","Arizona":"2,664","Arkansas":"1,526","California":"4,526","Colorado":"5,355","Connecticut":"0","Delaware":"0","DC":"94","Florida":"2,944","Georgia":"2,403","Hawaii":"245","Idaho":"97","Illinois":"2,545","Indiana":"735","Iowa":"2,467","Kansas":"N/A","Kentucky":"525","Louisiana":"402","Maine":"0","Maryland":"672","Massachusetts":"1,237","Michigan":"152","Minnesota":"1,192","Mississippi":"251","Missouri":"22,577","Montana":"683","Nebraska":"2,821","Nevada":"247","New Hampshire":"0","New Jersey":"900","New Mexico":"401","New York":"2,807","North Carolina":"1,625","North Dakota":"373","Ohio":"735","Oklahoma":"5,607","Oregon":"570","Pennsylvania":"465","Rhode Island":"384","South Carolina":"176","South Dakota":"584","Tennessee":"1,754","Texas":"10,102","Utah":"845","Vermont":"71","Virginia":"1,812","Washington":"1,885","West Virginia":"0","Wisconsin":"125","Wyoming":"79","Puerto Rico":"308"},{"STATE":"Kentucky","Alabama":"2,272","Alaska":"361","Arizona":"1,177","Arkansas":"756","California":"6,594","Colorado":"2,721","Connecticut":"329","Delaware":"0","DC":"0","Florida":"9,255","Georgia":"4,845","Hawaii":"103","Idaho":"0","Illinois":"6,394","Indiana":"10,990","Iowa":"709","Kansas":"1,503","Kentucky":"N/A","Louisiana":"1,358","Maine":"411","Maryland":"1,087","Massachusetts":"530","Michigan":"3,005","Minnesota":"947","Mississippi":"1,710","Missouri":"2,379","Montana":"30","Nebraska":"103","Nevada":"695","New Hampshire":"679","New Jersey":"572","New Mexico":"101","New York":"3,404","North Carolina":"3,557","North Dakota":"282","Ohio":"13,426","Oklahoma":"600","Oregon":"285","Pennsylvania":"2,084","Rhode Island":"0","South Carolina":"1,375","South Dakota":"318","Tennessee":"12,132","Texas":"5,585","Utah":"874","Vermont":"0","Virginia":"3,145","Washington":"313","West Virginia":"2,929","Wisconsin":"1,313","Wyoming":"0","Puerto Rico":"2,194"},{"STATE":"Louisiana","Alabama":"5,658","Alaska":"359","Arizona":"857","Arkansas":"1,471","California":"4,654","Colorado":"2,529","Connecticut":"192","Delaware":"0","DC":"54","Florida":"3,597","Georgia":"3,280","Hawaii":"292","Idaho":"464","Illinois":"2,556","Indiana":"270","Iowa":"1,315","Kansas":"1,497","Kentucky":"276","Louisiana":"N/A","Maine":"35","Maryland":"248","Massachusetts":"1,024","Michigan":"1,026","Minnesota":"415","Mississippi":"8,208","Missouri":"1,005","Montana":"606","Nebraska":"145","Nevada":"112","New Hampshire":"0","New Jersey":"552","New Mexico":"158","New York":"1,882","North Carolina":"4,565","North Dakota":"0","Ohio":"1,373","Oklahoma":"1,807","Oregon":"607","Pennsylvania":"965","Rhode Island":"170","South Carolina":"992","South Dakota":"118","Tennessee":"2,184","Texas":"21,925","Utah":"280","Vermont":"122","Virginia":"2,548","Washington":"1,516","West Virginia":"586","Wisconsin":"714","Wyoming":"162","Puerto Rico":"186"},{"STATE":"Maine","Alabama":"471","Alaska":"7","Arizona":"257","Arkansas":"0","California":"1,315","Colorado":"407","Connecticut":"1,664","Delaware":"26","DC":"162","Florida":"2,967","Georgia":"248","Hawaii":"579","Idaho":"13","Illinois":"448","Indiana":"114","Iowa":"473","Kansas":"41","Kentucky":"429","Louisiana":"118","Maine":"N/A","Maryland":"332","Massachusetts":"7,799","Michigan":"256","Minnesota":"224","Mississippi":"0","Missouri":"1,163","Montana":"26","Nebraska":"0","Nevada":"0","New Hampshire":"5,649","New Jersey":"1,888","New Mexico":"160","New York":"1,896","North Carolina":"1,042","North Dakota":"429","Ohio":"236","Oklahoma":"143","Oregon":"188","Pennsylvania":"986","Rhode Island":"1,150","South Carolina":"345","South Dakota":"0","Tennessee":"461","Texas":"610","Utah":"589","Vermont":"661","Virginia":"1,276","Washington":"907","West Virginia":"107","Wisconsin":"328","Wyoming":"0","Puerto Rico":"0"},{"STATE":"Maryland","Alabama":"1,241","Alaska":"53","Arizona":"940","Arkansas":"349","California":"6,348","Colorado":"2,210","Connecticut":"707","Delaware":"5,674","DC":"19,754","Florida":"10,887","Georgia":"6,942","Hawaii":"1,595","Idaho":"108","Illinois":"1,193","Indiana":"468","Iowa":"326","Kansas":"655","Kentucky":"701","Louisiana":"406","Maine":"281","Maryland":"N/A","Massachusetts":"2,559","Michigan":"2,149","Minnesota":"661","Mississippi":"1,246","Missouri":"515","Montana":"65","Nebraska":"427","Nevada":"512","New Hampshire":"61","New Jersey":"7,411","New Mexico":"1,416","New York":"11,622","North Carolina":"7,845","North Dakota":"62","Ohio":"4,295","Oklahoma":"382","Oregon":"522","Pennsylvania":"13,462","Rhode Island":"928","South Carolina":"1,651","South Dakota":"198","Tennessee":"2,288","Texas":"5,229","Utah":"387","Vermont":"347","Virginia":"23,926","Washington":"2,176","West Virginia":"4,744","Wisconsin":"723","Wyoming":"0","Puerto Rico":"1,214"},{"STATE":"Massachusetts","Alabama":"681","Alaska":"115","Arizona":"2,511","Arkansas":"388","California":"12,831","Colorado":"3,046","Connecticut":"11,229","Delaware":"308","DC":"1,398","Florida":"11,295","Georgia":"2,517","Hawaii":"457","Idaho":"96","Illinois":"6,227","Indiana":"1,282","Iowa":"378","Kansas":"1,021","Kentucky":"689","Louisiana":"890","Maine":"3,360","Maryland":"2,836","Massachusetts":"N/A","Michigan":"1,629","Minnesota":"561","Mississippi":"50","Missouri":"1,259","Montana":"0","Nebraska":"598","Nevada":"355","New Hampshire":"10,579","New Jersey":"5,980","New Mexico":"799","New York":"21,876","North Carolina":"3,661","North Dakota":"0","Ohio":"2,259","Oklahoma":"1,180","Oregon":"699","Pennsylvania":"7,188","Rhode Island":"9,776","South Carolina":"1,720","South Dakota":"137","Tennessee":"780","Texas":"3,446","Utah":"524","Vermont":"3,226","Virginia":"4,166","Washington":"1,463","West Virginia":"292","Wisconsin":"1,484","Wyoming":"166","Puerto Rico":"4,448"},{"STATE":"Michigan","Alabama":"2,287","Alaska":"285","Arizona":"4,061","Arkansas":"806","California":"8,001","Colorado":"2,120","Connecticut":"912","Delaware":"286","DC":"642","Florida":"14,302","Georgia":"6,090","Hawaii":"410","Idaho":"2,441","Illinois":"13,818","Indiana":"10,775","Iowa":"613","Kansas":"669","Kentucky":"2,351","Louisiana":"643","Maine":"444","Maryland":"2,091","Massachusetts":"2,604","Michigan":"N/A","Minnesota":"2,661","Mississippi":"2,885","Missouri":"3,217","Montana":"1,156","Nebraska":"963","Nevada":"1,742","New Hampshire":"384","New Jersey":"2,295","New Mexico":"85","New York":"6,627","North Carolina":"5,848","North Dakota":"120","Ohio":"16,222","Oklahoma":"984","Oregon":"743","Pennsylvania":"3,144","Rhode Island":"447","South Carolina":"2,129","South Dakota":"80","Tennessee":"5,154","Texas":"10,484","Utah":"718","Vermont":"424","Virginia":"1,989","Washington":"1,849","West Virginia":"435","Wisconsin":"5,058","Wyoming":"1,380","Puerto Rico":"1,030"},{"STATE":"Minnesota","Alabama":"115","Alaska":"334","Arizona":"4,475","Arkansas":"484","California":"6,232","Colorado":"4,691","Connecticut":"407","Delaware":"65","DC":"239","Florida":"2,999","Georgia":"2,468","Hawaii":"393","Idaho":"407","Illinois":"9,753","Indiana":"1,769","Iowa":"5,329","Kansas":"2,295","Kentucky":"491","Louisiana":"488","Maine":"115","Maryland":"730","Massachusetts":"1,141","Michigan":"2,240","Minnesota":"N/A","Mississippi":"137","Missouri":"2,321","Montana":"541","Nebraska":"1,973","Nevada":"561","New Hampshire":"175","New Jersey":"417","New Mexico":"255","New York":"1,626","North Carolina":"1,307","North Dakota":"10,745","Ohio":"2,570","Oklahoma":"1,542","Oregon":"1,060","Pennsylvania":"1,180","Rhode Island":"0","South Carolina":"403","South Dakota":"5,127","Tennessee":"1,393","Texas":"4,849","Utah":"1,828","Vermont":"40","Virginia":"1,071","Washington":"2,666","West Virginia":"331","Wisconsin":"18,683","Wyoming":"846","Puerto Rico":"60"},{"STATE":"Mississippi","Alabama":"5,125","Alaska":"0","Arizona":"544","Arkansas":"3,244","California":"4,317","Colorado":"441","Connecticut":"101","Delaware":"0","DC":"182","Florida":"4,046","Georgia":"2,150","Hawaii":"389","Idaho":"908","Illinois":"3,383","Indiana":"814","Iowa":"163","Kansas":"203","Kentucky":"1,623","Louisiana":"5,777","Maine":"0","Maryland":"519","Massachusetts":"58","Michigan":"1,298","Minnesota":"81","Mississippi":"N/A","Missouri":"1,034","Montana":"29","Nebraska":"721","Nevada":"465","New Hampshire":"82","New Jersey":"199","New Mexico":"155","New York":"570","North Carolina":"2,485","North Dakota":"24","Ohio":"1,204","Oklahoma":"765","Oregon":"617","Pennsylvania":"737","Rhode Island":"12","South Carolina":"1,129","South Dakota":"0","Tennessee":"10,017","Texas":"4,046","Utah":"48","Vermont":"0","Virginia":"1,230","Washington":"1,989","West Virginia":"260","Wisconsin":"1,455","Wyoming":"0","Puerto Rico":"910"},{"STATE":"Missouri","Alabama":"2,283","Alaska":"1,288","Arizona":"2,958","Arkansas":"8,523","California":"7,037","Colorado":"4,960","Connecticut":"445","Delaware":"651","DC":"266","Florida":"5,881","Georgia":"3,902","Hawaii":"508","Idaho":"535","Illinois":"25,906","Indiana":"2,622","Iowa":"5,799","Kansas":"19,812","Kentucky":"2,895","Louisiana":"2,873","Maine":"221","Maryland":"1,244","Massachusetts":"688","Michigan":"4,371","Minnesota":"1,893","Mississippi":"2,988","Missouri":"N/A","Montana":"0","Nebraska":"2,764","Nevada":"1,194","New Hampshire":"142","New Jersey":"630","New Mexico":"1,045","New York":"2,519","North Carolina":"1,802","North Dakota":"815","Ohio":"3,333","Oklahoma":"4,221","Oregon":"1,734","Pennsylvania":"3,053","Rhode Island":"117","South Carolina":"2,490","South Dakota":"838","Tennessee":"4,026","Texas":"11,488","Utah":"1,272","Vermont":"61","Virginia":"2,918","Washington":"2,916","West Virginia":"514","Wisconsin":"1,828","Wyoming":"540","Puerto Rico":"684"},{"STATE":"Montana","Alabama":"296","Alaska":"608","Arizona":"1,416","Arkansas":"340","California":"5,173","Colorado":"2,521","Connecticut":"69","Delaware":"0","DC":"0","Florida":"714","Georgia":"390","Hawaii":"18","Idaho":"1,744","Illinois":"1,171","Indiana":"284","Iowa":"114","Kansas":"240","Kentucky":"43","Louisiana":"285","Maine":"11","Maryland":"750","Massachusetts":"77","Michigan":"234","Minnesota":"2,089","Mississippi":"359","Missouri":"158","Montana":"N/A","Nebraska":"115","Nevada":"979","New Hampshire":"21","New Jersey":"0","New Mexico":"694","New York":"142","North Carolina":"350","North Dakota":"1,378","Ohio":"174","Oklahoma":"919","Oregon":"1,636","Pennsylvania":"428","Rhode Island":"0","South Carolina":"288","South Dakota":"160","Tennessee":"138","Texas":"2,177","Utah":"1,343","Vermont":"114","Virginia":"0","Washington":"5,132","West Virginia":"110","Wisconsin":"939","Wyoming":"1,434","Puerto Rico":"0"},{"STATE":"Nebraska","Alabama":"227","Alaska":"549","Arizona":"1,264","Arkansas":"568","California":"3,661","Colorado":"5,557","Connecticut":"1,269","Delaware":"46","DC":"70","Florida":"2,364","Georgia":"861","Hawaii":"155","Idaho":"442","Illinois":"2,415","Indiana":"381","Iowa":"5,863","Kansas":"3,393","Kentucky":"182","Louisiana":"126","Maine":"22","Maryland":"669","Massachusetts":"143","Michigan":"660","Minnesota":"1,656","Mississippi":"455","Missouri":"2,193","Montana":"164","Nebraska":"N/A","Nevada":"589","New Hampshire":"255","New Jersey":"852","New Mexico":"386","New York":"585","North Carolina":"466","North Dakota":"676","Ohio":"297","Oklahoma":"751","Oregon":"314","Pennsylvania":"483","Rhode Island":"988","South Carolina":"502","South Dakota":"1,617","Tennessee":"270","Texas":"2,702","Utah":"1,064","Vermont":"0","Virginia":"935","Washington":"812","West Virginia":"45","Wisconsin":"223","Wyoming":"1,281","Puerto Rico":"0"},{"STATE":"Nevada","Alabama":"394","Alaska":"562","Arizona":"5,741","Arkansas":"534","California":"45,482","Colorado":"3,293","Connecticut":"499","Delaware":"97","DC":"0","Florida":"4,997","Georgia":"2,474","Hawaii":"6,067","Idaho":"1,013","Illinois":"2,963","Indiana":"835","Iowa":"737","Kansas":"727","Kentucky":"1,268","Louisiana":"714","Maine":"493","Maryland":"258","Massachusetts":"391","Michigan":"2,272","Minnesota":"1,320","Mississippi":"138","Missouri":"1,151","Montana":"664","Nebraska":"492","Nevada":"N/A","New Hampshire":"221","New Jersey":"2,467","New Mexico":"1,406","New York":"4,742","North Carolina":"1,268","North Dakota":"333","Ohio":"1,074","Oklahoma":"221","Oregon":"906","Pennsylvania":"1,016","Rhode Island":"218","South Carolina":"1,310","South Dakota":"777","Tennessee":"1,189","Texas":"3,343","Utah":"3,260","Vermont":"37","Virginia":"1,307","Washington":"4,639","West Virginia":"14","Wisconsin":"889","Wyoming":"1,686","Puerto Rico":"399"},{"STATE":"New Hampshire","Alabama":"174","Alaska":"740","Arizona":"678","Arkansas":"0","California":"953","Colorado":"1,008","Connecticut":"2,435","Delaware":"0","DC":"83","Florida":"2,128","Georgia":"1,174","Hawaii":"360","Idaho":"125","Illinois":"144","Indiana":"197","Iowa":"237","Kansas":"317","Kentucky":"0","Louisiana":"29","Maine":"3,353","Maryland":"647","Massachusetts":"21,063","Michigan":"409","Minnesota":"247","Mississippi":"368","Missouri":"364","Montana":"32","Nebraska":"90","Nevada":"398","New Hampshire":"N/A","New Jersey":"396","New Mexico":"0","New York":"3,869","North Carolina":"1,113","North Dakota":"0","Ohio":"416","Oklahoma":"67","Oregon":"0","Pennsylvania":"1,799","Rhode Island":"932","South Carolina":"0","South Dakota":"0","Tennessee":"95","Texas":"1,527","Utah":"613","Vermont":"2,789","Virginia":"696","Washington":"11","West Virginia":"297","Wisconsin":"84","Wyoming":"0","Puerto Rico":"202"},{"STATE":"New Jersey","Alabama":"48","Alaska":"299","Arizona":"1,013","Arkansas":"137","California":"8,239","Colorado":"1,364","Connecticut":"3,884","Delaware":"1,809","DC":"736","Florida":"10,399","Georgia":"2,985","Hawaii":"551","Idaho":"0","Illinois":"1,633","Indiana":"1,147","Iowa":"110","Kansas":"560","Kentucky":"138","Louisiana":"567","Maine":"483","Maryland":"5,168","Massachusetts":"3,458","Michigan":"1,445","Minnesota":"508","Mississippi":"267","Missouri":"1,410","Montana":"479","Nebraska":"290","Nevada":"365","New Hampshire":"112","New Jersey":"N/A","New Mexico":"141","New York":"48,558","North Carolina":"3,436","North Dakota":"263","Ohio":"2,166","Oklahoma":"285","Oregon":"192","Pennsylvania":"23,566","Rhode Island":"129","South Carolina":"1,520","South Dakota":"318","Tennessee":"1,608","Texas":"5,554","Utah":"104","Vermont":"360","Virginia":"5,341","Washington":"534","West Virginia":"350","Wisconsin":"330","Wyoming":"0","Puerto Rico":"3,694"},{"STATE":"New Mexico","Alabama":"732","Alaska":"749","Arizona":"7,350","Arkansas":"552","California":"4,939","Colorado":"4,293","Connecticut":"305","Delaware":"308","DC":"105","Florida":"2,411","Georgia":"894","Hawaii":"429","Idaho":"382","Illinois":"452","Indiana":"324","Iowa":"105","Kansas":"292","Kentucky":"338","Louisiana":"469","Maine":"353","Maryland":"1,546","Massachusetts":"482","Michigan":"1,390","Minnesota":"811","Mississippi":"0","Missouri":"1,700","Montana":"170","Nebraska":"0","Nevada":"1,319","New Hampshire":"629","New Jersey":"397","New Mexico":"N/A","New York":"1,638","North Carolina":"987","North Dakota":"0","Ohio":"869","Oklahoma":"1,022","Oregon":"884","Pennsylvania":"1,748","Rhode Island":"3","South Carolina":"585","South Dakota":"10","Tennessee":"1,723","Texas":"17,155","Utah":"625","Vermont":"0","Virginia":"801","Washington":"1,843","West Virginia":"153","Wisconsin":"332","Wyoming":"198","Puerto Rico":"92"},{"STATE":"New York","Alabama":"402","Alaska":"421","Arizona":"4,971","Arkansas":"755","California":"22,626","Colorado":"3,463","Connecticut":"16,339","Delaware":"1,069","DC":"3,042","Florida":"23,515","Georgia":"5,180","Hawaii":"1,534","Idaho":"573","Illinois":"8,949","Indiana":"2,462","Iowa":"375","Kansas":"479","Kentucky":"1,688","Louisiana":"2,095","Maine":"1,596","Maryland":"8,332","Massachusetts":"17,877","Michigan":"3,551","Minnesota":"1,309","Mississippi":"802","Missouri":"2,918","Montana":"132","Nebraska":"181","Nevada":"435","New Hampshire":"2,044","New Jersey":"33,747","New Mexico":"665","New York":"N/A","North Carolina":"9,471","North Dakota":"306","Ohio":"6,648","Oklahoma":"1,396","Oregon":"2,506","Pennsylvania":"22,933","Rhode Island":"1,006","South Carolina":"4,716","South Dakota":"159","Tennessee":"3,661","Texas":"9,368","Utah":"1,068","Vermont":"3,895","Virginia":"10,761","Washington":"4,929","West Virginia":"1,503","Wisconsin":"2,787","Wyoming":"83","Puerto Rico":"7,385"},{"STATE":"North Carolina","Alabama":"3,491","Alaska":"2,059","Arizona":"3,539","Arkansas":"1,135","California":"17,653","Colorado":"4,285","Connecticut":"7,425","Delaware":"955","DC":"1,737","Florida":"32,234","Georgia":"24,882","Hawaii":"1,365","Idaho":"1,267","Illinois":"8,568","Indiana":"4,211","Iowa":"480","Kansas":"2,245","Kentucky":"3,409","Louisiana":"2,562","Maine":"1,324","Maryland":"9,671","Massachusetts":"5,116","Michigan":"6,818","Minnesota":"1,782","Mississippi":"1,509","Missouri":"4,563","Montana":"139","Nebraska":"164","Nevada":"2,111","New Hampshire":"1,548","New Jersey":"11,706","New Mexico":"462","New York":"29,702","North Carolina":"N/A","North Dakota":"668","Ohio":"9,665","Oklahoma":"2,997","Oregon":"1,263","Pennsylvania":"13,506","Rhode Island":"897","South Carolina":"32,088","South Dakota":"743","Tennessee":"8,233","Texas":"11,981","Utah":"1,271","Vermont":"608","Virginia":"35,641","Washington":"4,751","West Virginia":"3,722","Wisconsin":"2,600","Wyoming":"145","Puerto Rico":"1,631"},{"STATE":"North Dakota","Alabama":"193","Alaska":"151","Arizona":"681","Arkansas":"144","California":"1,797","Colorado":"500","Connecticut":"34","Delaware":"0","DC":"0","Florida":"230","Georgia":"196","Hawaii":"16","Idaho":"513","Illinois":"631","Indiana":"132","Iowa":"149","Kansas":"181","Kentucky":"86","Louisiana":"249","Maine":"0","Maryland":"0","Massachusetts":"62","Michigan":"369","Minnesota":"11,684","Mississippi":"422","Missouri":"563","Montana":"1,307","Nebraska":"922","Nevada":"183","New Hampshire":"385","New Jersey":"576","New Mexico":"144","New York":"133","North Carolina":"162","North Dakota":"N/A","Ohio":"174","Oklahoma":"339","Oregon":"347","Pennsylvania":"28","Rhode Island":"0","South Carolina":"0","South Dakota":"2,377","Tennessee":"177","Texas":"1,378","Utah":"38","Vermont":"0","Virginia":"251","Washington":"709","West Virginia":"144","Wisconsin":"556","Wyoming":"342","Puerto Rico":"1,049"},{"STATE":"Ohio","Alabama":"3,101","Alaska":"169","Arizona":"2,620","Arkansas":"873","California":"11,777","Colorado":"3,265","Connecticut":"1,340","Delaware":"452","DC":"784","Florida":"15,087","Georgia":"3,987","Hawaii":"771","Idaho":"31","Illinois":"12,463","Indiana":"11,578","Iowa":"389","Kansas":"1,622","Kentucky":"10,952","Louisiana":"2,017","Maine":"509","Maryland":"2,611","Massachusetts":"2,462","Michigan":"13,107","Minnesota":"2,793","Mississippi":"605","Missouri":"2,206","Montana":"617","Nebraska":"410","Nevada":"2,132","New Hampshire":"1,068","New Jersey":"4,520","New Mexico":"551","New York":"9,518","North Carolina":"8,822","North Dakota":"292","Ohio":"N/A","Oklahoma":"2,210","Oregon":"1,483","Pennsylvania":"14,425","Rhode Island":"667","South Carolina":"2,487","South Dakota":"217","Tennessee":"7,805","Texas":"8,712","Utah":"1,622","Vermont":"435","Virginia":"5,844","Washington":"3,423","West Virginia":"8,726","Wisconsin":"1,660","Wyoming":"179","Puerto Rico":"3,059"},{"STATE":"Oklahoma","Alabama":"176","Alaska":"328","Arizona":"1,912","Arkansas":"7,396","California":"11,302","Colorado":"3,698","Connecticut":"391","Delaware":"185","DC":"254","Florida":"3,155","Georgia":"2,542","Hawaii":"385","Idaho":"595","Illinois":"3,007","Indiana":"1,087","Iowa":"1,283","Kansas":"6,048","Kentucky":"1,331","Louisiana":"1,484","Maine":"82","Maryland":"569","Massachusetts":"205","Michigan":"1,577","Minnesota":"528","Mississippi":"865","Missouri":"5,253","Montana":"481","Nebraska":"145","Nevada":"627","New Hampshire":"393","New Jersey":"424","New Mexico":"1,011","New York":"2,051","North Carolina":"1,909","North Dakota":"212","Ohio":"1,282","Oklahoma":"N/A","Oregon":"635","Pennsylvania":"1,405","Rhode Island":"0","South Carolina":"1,108","South Dakota":"194","Tennessee":"1,309","Texas":"28,060","Utah":"783","Vermont":"61","Virginia":"1,312","Washington":"1,658","West Virginia":"174","Wisconsin":"829","Wyoming":"299","Puerto Rico":"272"},{"STATE":"Oregon","Alabama":"167","Alaska":"549","Arizona":"4,932","Arkansas":"921","California":"43,804","Colorado":"3,625","Connecticut":"1,127","Delaware":"159","DC":"606","Florida":"3,172","Georgia":"906","Hawaii":"3,302","Idaho":"4,576","Illinois":"2,245","Indiana":"1,052","Iowa":"215","Kansas":"1,748","Kentucky":"997","Louisiana":"769","Maine":"419","Maryland":"1,678","Massachusetts":"817","Michigan":"993","Minnesota":"724","Mississippi":"235","Missouri":"1,194","Montana":"2,827","Nebraska":"644","Nevada":"1,631","New Hampshire":"0","New Jersey":"978","New Mexico":"2,463","New York":"2,899","North Carolina":"2,142","North Dakota":"402","Ohio":"1,421","Oklahoma":"2,185","Oregon":"N/A","Pennsylvania":"1,958","Rhode Island":"156","South Carolina":"531","South Dakota":"608","Tennessee":"1,168","Texas":"5,377","Utah":"3,246","Vermont":"158","Virginia":"2,141","Washington":"24,207","West Virginia":"140","Wisconsin":"557","Wyoming":"563","Puerto Rico":"0"},{"STATE":"Pennsylvania","Alabama":"1,978","Alaska":"820","Arizona":"2,076","Arkansas":"979","California":"12,381","Colorado":"3,434","Connecticut":"6,629","Delaware":"5,168","DC":"1,908","Florida":"12,938","Georgia":"5,206","Hawaii":"588","Idaho":"629","Illinois":"5,341","Indiana":"1,559","Iowa":"936","Kansas":"1,154","Kentucky":"1,487","Louisiana":"513","Maine":"770","Maryland":"19,747","Massachusetts":"8,352","Michigan":"2,283","Minnesota":"1,557","Mississippi":"399","Missouri":"1,363","Montana":"171","Nebraska":"1,063","Nevada":"803","New Hampshire":"1,259","New Jersey":"40,118","New Mexico":"675","New York":"40,208","North Carolina":"9,251","North Dakota":"106","Ohio":"10,700","Oklahoma":"1,130","Oregon":"2,511","Pennsylvania":"N/A","Rhode Island":"1,204","South Carolina":"1,582","South Dakota":"162","Tennessee":"2,746","Texas":"12,497","Utah":"2,014","Vermont":"604","Virginia":"12,785","Washington":"3,772","West Virginia":"3,979","Wisconsin":"2,337","Wyoming":"188","Puerto Rico":"7,005"},{"STATE":"Rhode Island","Alabama":"53","Alaska":"0","Arizona":"360","Arkansas":"91","California":"1,484","Colorado":"421","Connecticut":"4,252","Delaware":"23","DC":"177","Florida":"2,778","Georgia":"390","Hawaii":"17","Idaho":"0","Illinois":"621","Indiana":"0","Iowa":"307","Kansas":"0","Kentucky":"41","Louisiana":"0","Maine":"209","Maryland":"623","Massachusetts":"9,077","Michigan":"696","Minnesota":"141","Mississippi":"135","Missouri":"87","Montana":"84","Nebraska":"196","Nevada":"97","New Hampshire":"923","New Jersey":"631","New Mexico":"0","New York":"2,631","North Carolina":"812","North Dakota":"113","Ohio":"318","Oklahoma":"58","Oregon":"90","Pennsylvania":"900","Rhode Island":"N/A","South Carolina":"348","South Dakota":"121","Tennessee":"581","Texas":"1,079","Utah":"60","Vermont":"337","Virginia":"714","Washington":"399","West Virginia":"0","Wisconsin":"325","Wyoming":"0","Puerto Rico":"40"},{"STATE":"South Carolina","Alabama":"2,823","Alaska":"411","Arizona":"1,708","Arkansas":"581","California":"4,846","Colorado":"1,947","Connecticut":"2,941","Delaware":"146","DC":"1,552","Florida":"13,371","Georgia":"16,234","Hawaii":"858","Idaho":"47","Illinois":"4,512","Indiana":"2,816","Iowa":"165","Kansas":"965","Kentucky":"1,312","Louisiana":"1,495","Maine":"779","Maryland":"6,900","Massachusetts":"3,027","Michigan":"3,206","Minnesota":"621","Mississippi":"760","Missouri":"1,168","Montana":"215","Nebraska":"90","Nevada":"180","New Hampshire":"1,143","New Jersey":"3,664","New Mexico":"139","New York":"10,230","North Carolina":"30,447","North Dakota":"595","Ohio":"6,634","Oklahoma":"1,192","Oregon":"663","Pennsylvania":"7,865","Rhode Island":"708","South Carolina":"N/A","South Dakota":"590","Tennessee":"3,709","Texas":"7,373","Utah":"424","Vermont":"0","Virginia":"8,081","Washington":"1,943","West Virginia":"2,403","Wisconsin":"1,243","Wyoming":"508","Puerto Rico":"595"},{"STATE":"South Dakota","Alabama":"0","Alaska":"346","Arizona":"732","Arkansas":"18","California":"2,929","Colorado":"820","Connecticut":"0","Delaware":"0","DC":"0","Florida":"758","Georgia":"128","Hawaii":"0","Idaho":"108","Illinois":"757","Indiana":"844","Iowa":"2,887","Kansas":"1,123","Kentucky":"52","Louisiana":"127","Maine":"0","Maryland":"26","Massachusetts":"271","Michigan":"145","Minnesota":"4,991","Mississippi":"125","Missouri":"500","Montana":"468","Nebraska":"1,803","Nevada":"98","New Hampshire":"0","New Jersey":"0","New Mexico":"389","New York":"89","North Carolina":"100","North Dakota":"1,858","Ohio":"788","Oklahoma":"23","Oregon":"236","Pennsylvania":"147","Rhode Island":"448","South Carolina":"0","South Dakota":"N/A","Tennessee":"147","Texas":"1,946","Utah":"662","Vermont":"0","Virginia":"720","Washington":"976","West Virginia":"131","Wisconsin":"1,026","Wyoming":"2,047","Puerto Rico":"0"},{"STATE":"Tennessee","Alabama":"7,683","Alaska":"1,141","Arizona":"1,449","Arkansas":"5,583","California":"7,996","Colorado":"1,692","Connecticut":"2,042","Delaware":"185","DC":"295","Florida":"14,926","Georgia":"16,367","Hawaii":"1,397","Idaho":"219","Illinois":"9,737","Indiana":"6,736","Iowa":"646","Kansas":"1,597","Kentucky":"12,562","Louisiana":"2,004","Maine":"2,799","Maryland":"794","Massachusetts":"2,130","Michigan":"3,954","Minnesota":"2,484","Mississippi":"8,739","Missouri":"3,287","Montana":"662","Nebraska":"216","Nevada":"274","New Hampshire":"340","New Jersey":"1,659","New Mexico":"159","New York":"4,905","North Carolina":"5,933","North Dakota":"61","Ohio":"7,210","Oklahoma":"1,486","Oregon":"647","Pennsylvania":"2,723","Rhode Island":"0","South Carolina":"2,173","South Dakota":"207","Tennessee":"N/A","Texas":"11,827","Utah":"181","Vermont":"309","Virginia":"6,681","Washington":"2,187","West Virginia":"1,249","Wisconsin":"1,309","Wyoming":"25","Puerto Rico":"667"},{"STATE":"Texas","Alabama":"6,915","Alaska":"2,257","Arizona":"20,322","Arkansas":"11,986","California":"69,945","Colorado":"21,596","Connecticut":"1,834","Delaware":"2,012","DC":"1,624","Florida":"31,145","Georgia":"16,174","Hawaii":"3,630","Idaho":"2,668","Illinois":"21,848","Indiana":"10,084","Iowa":"6,600","Kansas":"10,670","Kentucky":"7,090","Louisiana":"27,998","Maine":"1,544","Maryland":"7,112","Massachusetts":"5,636","Michigan":"10,036","Minnesota":"6,795","Mississippi":"8,825","Missouri":"13,946","Montana":"1,974","Nebraska":"6,201","Nevada":"6,499","New Hampshire":"1,542","New Jersey":"8,723","New Mexico":"13,041","New York":"18,209","North Carolina":"12,463","North Dakota":"2,026","Ohio":"9,363","Oklahoma":"30,532","Oregon":"3,704","Pennsylvania":"11,769","Rhode Island":"1,361","South Carolina":"7,969","South Dakota":"860","Tennessee":"15,565","Texas":"N/A","Utah":"9,082","Vermont":"252","Virginia":"19,660","Washington":"14,335","West Virginia":"915","Wisconsin":"4,927","Wyoming":"732","Puerto Rico":"9,246"},{"STATE":"Utah","Alabama":"125","Alaska":"2,350","Arizona":"9,140","Arkansas":"1,136","California":"23,034","Colorado":"3,615","Connecticut":"1,024","Delaware":"184","DC":"490","Florida":"2,707","Georgia":"1,541","Hawaii":"1,516","Idaho":"9,520","Illinois":"1,440","Indiana":"1,349","Iowa":"373","Kansas":"510","Kentucky":"1,142","Louisiana":"878","Maine":"63","Maryland":"812","Massachusetts":"390","Michigan":"1,340","Minnesota":"811","Mississippi":"186","Missouri":"2,103","Montana":"1,637","Nebraska":"523","Nevada":"5,181","New Hampshire":"0","New Jersey":"702","New Mexico":"871","New York":"2,511","North Carolina":"1,921","North Dakota":"1,266","Ohio":"833","Oklahoma":"1,194","Oregon":"2,790","Pennsylvania":"1,992","Rhode Island":"0","South Carolina":"766","South Dakota":"795","Tennessee":"964","Texas":"7,467","Utah":"N/A","Vermont":"221","Virginia":"1,392","Washington":"5,074","West Virginia":"51","Wisconsin":"398","Wyoming":"755","Puerto Rico":"59"},{"STATE":"Vermont","Alabama":"0","Alaska":"0","Arizona":"337","Arkansas":"0","California":"1,018","Colorado":"350","Connecticut":"1,076","Delaware":"29","DC":"62","Florida":"876","Georgia":"14","Hawaii":"41","Idaho":"0","Illinois":"187","Indiana":"3","Iowa":"82","Kansas":"0","Kentucky":"66","Louisiana":"0","Maine":"988","Maryland":"540","Massachusetts":"3,731","Michigan":"59","Minnesota":"7","Mississippi":"0","Missouri":"45","Montana":"0","Nebraska":"0","Nevada":"0","New Hampshire":"3,285","New Jersey":"1,393","New Mexico":"60","New York":"3,186","North Carolina":"331","North Dakota":"41","Ohio":"118","Oklahoma":"0","Oregon":"395","Pennsylvania":"1,449","Rhode Island":"262","South Carolina":"38","South Dakota":"619","Tennessee":"6","Texas":"7","Utah":"77","Vermont":"N/A","Virginia":"242","Washington":"165","West Virginia":"23","Wisconsin":"54","Wyoming":"0","Puerto Rico":"0"},{"STATE":"Virginia","Alabama":"2,424","Alaska":"1,624","Arizona":"3,584","Arkansas":"519","California":"17,473","Colorado":"3,269","Connecticut":"5,158","Delaware":"1,382","DC":"8,692","Florida":"19,439","Georgia":"6,319","Hawaii":"3,548","Idaho":"148","Illinois":"7,719","Indiana":"2,276","Iowa":"229","Kansas":"771","Kentucky":"4,959","Louisiana":"2,296","Maine":"1,232","Maryland":"28,394","Massachusetts":"5,442","Michigan":"4,722","Minnesota":"1,194","Mississippi":"891","Missouri":"2,786","Montana":"106","Nebraska":"1,950","Nevada":"2,305","New Hampshire":"641","New Jersey":"7,715","New Mexico":"2,067","New York":"14,827","North Carolina":"22,598","North Dakota":"80","Ohio":"7,689","Oklahoma":"3,693","Oregon":"904","Pennsylvania":"14,122","Rhode Island":"1,270","South Carolina":"8,354","South Dakota":"142","Tennessee":"7,491","Texas":"15,873","Utah":"1,507","Vermont":"872","Virginia":"N/A","Washington":"4,925","West Virginia":"6,618","Wisconsin":"1,877","Wyoming":"48","Puerto Rico":"2,001"},{"STATE":"Washington","Alabama":"1,465","Alaska":"5,374","Arizona":"12,801","Arkansas":"823","California":"51,485","Colorado":"13,012","Connecticut":"1,309","Delaware":"277","DC":"748","Florida":"9,093","Georgia":"2,804","Hawaii":"4,497","Idaho":"11,619","Illinois":"7,422","Indiana":"1,296","Iowa":"784","Kansas":"2,568","Kentucky":"2,042","Louisiana":"1,109","Maine":"266","Maryland":"2,733","Massachusetts":"4,715","Michigan":"4,472","Minnesota":"4,153","Mississippi":"689","Missouri":"3,327","Montana":"4,707","Nebraska":"1,428","Nevada":"3,551","New Hampshire":"785","New Jersey":"3,287","New Mexico":"2,232","New York":"7,083","North Carolina":"7,250","North Dakota":"2,021","Ohio":"2,834","Oklahoma":"2,041","Oregon":"32,384","Pennsylvania":"1,556","Rhode Island":"373","South Carolina":"1,374","South Dakota":"1,156","Tennessee":"3,672","Texas":"16,005","Utah":"5,404","Vermont":"743","Virginia":"3,834","Washington":"N/A","West Virginia":"319","Wisconsin":"1,940","Wyoming":"866","Puerto Rico":"480"},{"STATE":"West Virginia","Alabama":"284","Alaska":"11","Arizona":"57","Arkansas":"195","California":"1,095","Colorado":"464","Connecticut":"631","Delaware":"0","DC":"490","Florida":"1,992","Georgia":"1,650","Hawaii":"0","Idaho":"48","Illinois":"354","Indiana":"343","Iowa":"64","Kansas":"205","Kentucky":"1,654","Louisiana":"357","Maine":"597","Maryland":"7,100","Massachusetts":"21","Michigan":"572","Minnesota":"0","Mississippi":"152","Missouri":"123","Montana":"39","Nebraska":"0","Nevada":"293","New Hampshire":"135","New Jersey":"481","New Mexico":"81","New York":"1,320","North Carolina":"2,419","North Dakota":"134","Ohio":"7,281","Oklahoma":"12","Oregon":"0","Pennsylvania":"6,226","Rhode Island":"0","South Carolina":"435","South Dakota":"124","Tennessee":"1,903","Texas":"1,345","Utah":"179","Vermont":"0","Virginia":"6,114","Washington":"216","West Virginia":"N/A","Wisconsin":"0","Wyoming":"0","Puerto Rico":"112"},{"STATE":"Wisconsin","Alabama":"966","Alaska":"738","Arizona":"3,364","Arkansas":"1,397","California":"6,830","Colorado":"4,129","Connecticut":"344","Delaware":"0","DC":"215","Florida":"5,242","Georgia":"708","Hawaii":"323","Idaho":"1,400","Illinois":"31,323","Indiana":"3,481","Iowa":"3,383","Kansas":"401","Kentucky":"992","Louisiana":"745","Maine":"63","Maryland":"574","Massachusetts":"1,058","Michigan":"5,433","Minnesota":"18,036","Mississippi":"90","Missouri":"1,619","Montana":"159","Nebraska":"469","Nevada":"1,126","New Hampshire":"417","New Jersey":"521","New Mexico":"710","New York":"1,484","North Carolina":"1,152","North Dakota":"614","Ohio":"2,129","Oklahoma":"1,404","Oregon":"1,383","Pennsylvania":"1,525","Rhode Island":"81","South Carolina":"518","South Dakota":"872","Tennessee":"1,096","Texas":"4,526","Utah":"1,237","Vermont":"138","Virginia":"2,235","Washington":"1,634","West Virginia":"110","Wisconsin":"N/A","Wyoming":"420","Puerto Rico":"1,619"},{"STATE":"Wyoming","Alabama":"265","Alaska":"524","Arizona":"352","Arkansas":"77","California":"1,586","Colorado":"4,227","Connecticut":"0","Delaware":"0","DC":"0","Florida":"187","Georgia":"1","Hawaii":"0","Idaho":"1,074","Illinois":"150","Indiana":"119","Iowa":"568","Kansas":"291","Kentucky":"437","Louisiana":"150","Maine":"66","Maryland":"7","Massachusetts":"0","Michigan":"325","Minnesota":"473","Mississippi":"0","Missouri":"16","Montana":"1,307","Nebraska":"852","Nevada":"111","New Hampshire":"0","New Jersey":"503","New Mexico":"799","New York":"57","North Carolina":"46","North Dakota":"843","Ohio":"318","Oklahoma":"672","Oregon":"609","Pennsylvania":"2,660","Rhode Island":"1","South Carolina":"337","South Dakota":"853","Tennessee":"10","Texas":"1,914","Utah":"1,312","Vermont":"0","Virginia":"90","Washington":"1,426","West Virginia":"169","Wisconsin":"687","Wyoming":"N/A","Puerto Rico":"0"},{"STATE":"Puerto Rico","Alabama":"49","Alaska":"0","Arizona":"188","Arkansas":"109","California":"200","Colorado":"40","Connecticut":"580","Delaware":"259","DC":"0","Florida":"4,548","Georgia":"206","Hawaii":"63","Idaho":"0","Illinois":"802","Indiana":"0","Iowa":"0","Kansas":"0","Kentucky":"433","Louisiana":"96","Maine":"0","Maryland":"164","Massachusetts":"3,060","Michigan":"206","Minnesota":"0","Mississippi":"0","Missouri":"0","Montana":"0","Nebraska":"0","Nevada":"0","New Hampshire":"46","New Jersey":"1,451","New Mexico":"0","New York":"3,416","North Carolina":"42","North Dakota":"0","Ohio":"0","Oklahoma":"20","Oregon":"0","Pennsylvania":"3,296","Rhode Island":"0","South Carolina":"163","South Dakota":"0","Tennessee":"143","Texas":"1,008","Utah":"0","Vermont":"0","Virginia":"67","Washington":"368","West Virginia":"0","Wisconsin":"173","Wyoming":"0","Puerto Rico":"N/A"}]
